buildzr/__about__.py
buildzr/__init__.py
buildzr/dsl/__init__.py
buildzr/dsl/color.py
buildzr/dsl/dsl.py
buildzr/dsl/explorer.py
buildzr/dsl/expression.py
buildzr/dsl/relations.py
buildzr/dsl/factory/__init__.py
buildzr/dsl/factory/gen_id.py
buildzr/dsl/interfaces/__init__.py
buildzr/dsl/interfaces/interfaces.py
buildzr/encoders/__init__.py
buildzr/encoders/encoder.py
buildzr/exporters/__init__.py
buildzr/exporters/download_jars.py
buildzr/exporters/jar_locator.py
buildzr/exporters/workspace_converter.py
buildzr/jars/.gitignore
buildzr/jars/commons-logging.jar
buildzr/jars/plantuml.jar
buildzr/jars/structurizr-core.jar
buildzr/jars/structurizr-export.jar
buildzr/loaders/__init__.py
buildzr/loaders/json_loader.py
buildzr/models/__init__.py
buildzr/models/generate.sh
buildzr/models/models.py
buildzr/sinks/__init__.py
buildzr/sinks/interfaces.py
buildzr/sinks/json_sink.py
buildzr/sinks/plantuml_sink.py
buildzr/themes/__init__.py
buildzr/themes/base.py
buildzr/themes/generate.py
buildzr/themes/themes.txt
buildzr/themes/generated/__init__.py
buildzr/themes/generated/aws.py
buildzr/themes/generated/azure.py
buildzr/themes/generated/google_cloud.py
buildzr/themes/generated/kubernetes.py
buildzr/themes/generated/oracle_cloud.py
buildzr-0.0.30.dist-info/METADATA
buildzr-0.0.30.dist-info/WHEEL
buildzr-0.0.30.dist-info/licenses/LICENSE.md
buildzr-0.0.30.dist-info/RECORD
