Metadata-Version: 2.4
Name: buildzr
Version: 0.0.30
Summary: Structurizr for the `buildzr`s 🧱⚒️
Project-URL: homepage, https://github.com/amirulmenjeni/buildzr
Project-URL: issues, https://github.com/amirulmenjeni/buildzr/issues
Author-email: Amirul Menjeni <amirulmenjeni@pm.me>
License-File: LICENSE.md
Keywords: architecture,buildzr,c4model,design,diagram,structurizr
Classifier: Development Status :: 3 - Alpha
Classifier: License :: OSI Approved :: MIT License
Classifier: Operating System :: OS Independent
Classifier: Programming Language :: Python :: 3
Classifier: Programming Language :: Python :: 3.10
Classifier: Programming Language :: Python :: 3.11
Classifier: Programming Language :: Python :: 3.12
Requires-Python: >=3.10
Requires-Dist: pyhumps==3.8.0
Requires-Dist: pytest>=8.3.3
Provides-Extra: dev
Requires-Dist: datamodel-code-generator==0.26.2; extra == 'dev'
Requires-Dist: jsondiff==2.0.0; extra == 'dev'
Requires-Dist: mypy-extensions==1.0.0; extra == 'dev'
Requires-Dist: mypy==1.11.2; extra == 'dev'
Requires-Dist: pytest-mypy==0.10.3; extra == 'dev'
Requires-Dist: yq==3.4.3; extra == 'dev'
Provides-Extra: docs
Requires-Dist: mkdocs-material>=9.0.0; extra == 'docs'
Requires-Dist: mkdocs>=1.5.0; extra == 'docs'
Requires-Dist: mkdocstrings[python]>=0.24.0; extra == 'docs'
Requires-Dist: pymdown-extensions>=10.0; extra == 'docs'
Provides-Extra: export-plantuml
Requires-Dist: jpype1>=1.4.0; extra == 'export-plantuml'
